README.md
helper.yml
milestone_2.py
milestone_3.py
milestone_4.py
milestone_5.py
setup.py
test.txt
hangman/hangman_Template.py
hangman/hangman_solution.py
hangman/test_milestone1.py
hangman/test_milestone2.py
hangman/test_milestone3.py
hangman/test_milestone4.py
hangman/verify_milestone1.py
hangman/verify_milestone2.py
hangman/verify_milestone3.py
hangman/verify_milestone4.py
hangman_marking_aicore_test.egg-info/PKG-INFO
hangman_marking_aicore_test.egg-info/SOURCES.txt
hangman_marking_aicore_test.egg-info/dependency_links.txt
hangman_marking_aicore_test.egg-info/requires.txt
hangman_marking_aicore_test.egg-info/top_level.txt
hangman_test/__init__.py
hangman_test/ast_parser.py
hangman_test/test_milestone2_p1.py
hangman_test/test_milestone2_p2.py
hangman_test/test_milestone3_p1.py
hangman_test/test_milestone3_p2.py
hangman_test/test_milestone4_p1.py
hangman_test/test_milestone4_p2.py
hangman_test/test_milestone5_p1.py
hangman_test/test_milestone5_p2.py
hangman_test/verify.py
hangman_test/verify_milestone1.py
hangman_test/verify_milestone2_p1.py
hangman_test/verify_milestone2_p2.py
hangman_test/verify_milestone3_p1.py
hangman_test/verify_milestone3_p2.py
hangman_test/verify_milestone4_p1.py
hangman_test/verify_milestone4_p2.py
hangman_test/verify_milestone5_p1.py
hangman_test/verify_milestone5_p2.py