Metadata-Version: 2.1
Name: hangman-marking-aicore-test
Version: 1.0.10
Summary: An automated marking system for the hangman project (test)
Home-page: UNKNOWN
Author: Ivan Ying
Author-email: ivan@theaicore.com
License: UNKNOWN
Platform: UNKNOWN
Requires-Python: >=3.6
